LICENSE
README.md
setup.cfg
setup.py
hdbpp/__init__.py
hdbpp/abstract.py
hdbpp/reader.py
hdbpp.egg-info/PKG-INFO
hdbpp.egg-info/SOURCES.txt
hdbpp.egg-info/dependency_links.txt
hdbpp.egg-info/entry_points.txt
hdbpp.egg-info/requires.txt
hdbpp.egg-info/top_level.txt
hdbpp/mariadb/__init__.py
hdbpp/mariadb/mariadb.py
hdbpp/mariadb/timeutils.py
hdbpp/qt/__init__.py
hdbpp/qt/plot.py
hdbpp/timescaledb/__init__.py
hdbpp/timescaledb/timescaledb.py