Metadata-Version: 2.1
Name: hdbpp
Version: 0.0.32
Summary: hdb++ python3 API
Home-page: https://gitlab.com/tango-controls/hdbpp/libhdbpp-python
Author: Sergi Rubio, Damien Lacoste
Author-email: info@tango-controls.org
License: LGPL-3+
Platform: UNKNOWN
Classifier: Programming Language :: Python :: 3
Requires-Python: >=3.5
Provides-Extra: timescaledb
